divicast/__init__.py
divicast/base/__init__.py
divicast/base/symbol.py
divicast/entities/daemon.py
divicast/entities/dizhi.py
divicast/entities/liushen.py
divicast/entities/relative.py
divicast/entities/tiangan.py
divicast/entities/trigram.py
divicast/entities/wuxing.py
divicast/hex.json
divicast/sixline/__init__.py
divicast/sixline/divinatory_symbol.py
divicast/sixline/output.py
divicast/sixline/schema.json
divicast-0.1.1.dist-info/WHEEL
divicast-0.1.1.dist-info/METADATA
divicast-0.1.1.dist-info/RECORD
