Metadata-Version: 2.3
Name: divicast
Version: 0.1.1
Summary: This is a metaphysical chart library, including six line
Author: Wáng Sōng
Author-email: Wáng Sōng <wangsquirrel@gmail.com>
License: MIT License
Requires-Dist: pydantic>=2.11.9
Requires-Dist: rich==14.0.0
Requires-Dist: tyme4py>=1.3.4
Requires-Python: >=3.12
Project-URL: Homepage, https://github.com/wangsquirrel/divicast
